tabsdata_mssql-1.5.0.data/purelib/tabsdata_mssql/__init__.py
tabsdata_mssql-1.5.0.data/purelib/tabsdata_mssql/_connector.py
tabsdata_mssql-1.5.0.data/purelib/tabsdata_mssql/assets/manifest/BANNER
tabsdata_mssql-1.5.0.data/purelib/tabsdata_mssql/assets/manifest/LICENSE
tabsdata_mssql-1.5.0.data/purelib/tabsdata_mssql/assets/manifest/README-PyPi.md
tabsdata_mssql-1.5.0.data/purelib/tabsdata_mssql/assets/manifest/RELEASE-NOTES
tabsdata_mssql-1.5.0.data/purelib/tabsdata_mssql/assets/manifest/SOURCETRACK.yaml
tabsdata_mssql-1.5.0.data/purelib/tabsdata_mssql/assets/manifest/THIRD-PARTY
tabsdata_mssql-1.5.0.data/purelib/tabsdata_mssql/assets/manifest/VERSION
tabsdata_mssql-1.5.0.dist-info/licenses/tabsdata_mssql/assets/manifest/LICENSE
tabsdata_mssql-1.5.0.dist-info/METADATA
tabsdata_mssql-1.5.0.dist-info/WHEEL
tabsdata_mssql-1.5.0.dist-info/top_level.txt
tabsdata_mssql-1.5.0.dist-info/RECORD
